dagster_delta/__init__.py
dagster_delta/config.py
dagster_delta/py.typed
dagster_delta/resources.py
dagster_delta/_db_io_manager/__init__.py
dagster_delta/_db_io_manager/custom_db_io_manager.py
dagster_delta/_db_io_manager/utils.py
dagster_delta/_handler/__init__.py
dagster_delta/_handler/base.py
dagster_delta/_handler/merge.py
dagster_delta/_handler/utils/__init__.py
dagster_delta/_handler/utils/date_format.py
dagster_delta/_handler/utils/dnf.py
dagster_delta/_handler/utils/predicates.py
dagster_delta/io_manager/__init__.py
dagster_delta/io_manager/arrow.py
dagster_delta/io_manager/base.py
dagster_delta/io_manager/polars.py
dagster_delta-0.5.3.dist-info/METADATA
dagster_delta-0.5.3.dist-info/WHEEL
dagster_delta-0.5.3.dist-info/licenses/LICENSE
dagster_delta-0.5.3.dist-info/RECORD
