Metadata-Version: 2.4
Name: dagster-delta
Version: 0.5.3
Summary: Deltalake IO Managers for Dagster with pyarrow and Polars support.
Author: Ion Koutsouris
License-File: LICENSE
Keywords: dagster,datalake,delta,deltalake,io manager,polars,pyarrow
Classifier: License :: OSI Approved :: Apache Software License
Classifier: Programming Language :: Python :: 3.9
Classifier: Programming Language :: Python :: 3.10
Classifier: Programming Language :: Python :: 3.11
Classifier: Programming Language :: Python :: 3.12
Requires-Python: >=3.9
Requires-Dist: dagster<2.0,>=1.8
Requires-Dist: deltalake>=1.0.0
Requires-Dist: pendulum>=3.0.0
Provides-Extra: polars
Requires-Dist: polars>=1.31.0; extra == 'polars'
